ipyjadwal/__init__.py
ipyjadwal-0.1.51.dist-info/licenses/LICENSE
ipyjadwal-0.1.51.dist-info/METADATA
ipyjadwal-0.1.51.dist-info/WHEEL
ipyjadwal-0.1.51.dist-info/top_level.txt
ipyjadwal-0.1.51.dist-info/RECORD
