Metadata-Version: 2.4
Name: ipyjadwal
Version: 0.1.51
Summary: A clean, interactive Google Sheet explorer for Colab (Jadwal)
Author: Mustafa Marzouk
License: MIT
Keywords: jupyter,widget,google sheets,colab,jadwal
Requires-Python: >=3.7
License-File: LICENSE
Requires-Dist: gspread>=5.0.0
Requires-Dist: pandas
Requires-Dist: ipywidgets
Requires-Dist: google-auth
Requires-Dist: ipython
Dynamic: author
Dynamic: description
Dynamic: description-content-type
Dynamic: keywords
Dynamic: license
Dynamic: license-file
Dynamic: requires-dist
Dynamic: requires-python
Dynamic: summary
